lsystem/__init__.py
lsystem/lsys_generator.py
lsystem/utils.py
lsystem_generator-1.0.dist-info/METADATA
lsystem_generator-1.0.dist-info/WHEEL
lsystem_generator-1.0.dist-info/top_level.txt
lsystem_generator-1.0.dist-info/RECORD
