Metadata-Version: 2.1
Name: lsystem-generator
Version: 1.0
Summary: Package for generating and rendering Lsystems
Home-page: UNKNOWN
Author: Camille Boillet
Author-email: camille.boillet@gmail.com
License: UNKNOWN
Platform: UNKNOWN
Classifier: Programming Language :: Python :: 3
Classifier: License :: Other/Proprietary License
Classifier: Operating System :: OS Independent
Requires-Python: >=3.9
Requires-Dist: numpy (>=1.19.4)
Requires-Dist: matplotlib (>=3.3.3)
Requires-Dist: Pillow (>=8.0.1)
